klaviyo_api_beta/__init__.py
klaviyo_api_beta/custom_retry.py
klaviyo_api_beta/wrapper.py
openapi_client/__init__.py
openapi_client/api_client.py
openapi_client/configuration.py
openapi_client/exceptions.py
openapi_client/model_utils.py
openapi_client/rest.py
openapi_client/api/__init__.py
openapi_client/api/campaigns_api.py
openapi_client/apis/__init__.py
openapi_client/model/__init__.py
openapi_client/model/audiences_sub_object.py
openapi_client/model/campaign_clone_query.py
openapi_client/model/campaign_clone_query_as_sub_resource.py
openapi_client/model/campaign_clone_query_as_sub_resource_attributes.py
openapi_client/model/campaign_create_query.py
openapi_client/model/campaign_create_query_as_sub_resource.py
openapi_client/model/campaign_create_query_as_sub_resource_attributes.py
openapi_client/model/campaign_message_assign_template_query.py
openapi_client/model/campaign_message_assign_template_query_as_sub_resource.py
openapi_client/model/campaign_message_assign_template_query_as_sub_resource_attributes.py
openapi_client/model/campaign_message_partial_update_query.py
openapi_client/model/campaign_message_partial_update_query_as_sub_resource.py
openapi_client/model/campaign_message_partial_update_query_as_sub_resource_attributes.py
openapi_client/model/campaign_partial_update_query.py
openapi_client/model/campaign_partial_update_query_as_sub_resource.py
openapi_client/model/campaign_partial_update_query_as_sub_resource_attributes.py
openapi_client/model/campaign_send_job_create_query.py
openapi_client/model/campaign_send_job_create_query_as_sub_resource.py
openapi_client/model/campaign_send_job_create_query_as_sub_resource_attributes.py
openapi_client/model/campaign_send_job_partial_update_query.py
openapi_client/model/campaign_send_job_partial_update_query_as_sub_resource.py
openapi_client/model/campaign_send_job_partial_update_query_as_sub_resource_attributes.py
openapi_client/model/catalog_category_create_job_create_query.py
klaviyo_api_beta-2.0.2.dist-info/LICENSE
klaviyo_api_beta-2.0.2.dist-info/METADATA
klaviyo_api_beta-2.0.2.dist-info/WHEEL
klaviyo_api_beta-2.0.2.dist-info/top_level.txt
klaviyo_api_beta-2.0.2.dist-info/RECORD
